MANIFEST.in
README.md
requirements.txt
setup.py
torch_genomics.egg-info/PKG-INFO
torch_genomics.egg-info/SOURCES.txt
torch_genomics.egg-info/dependency_links.txt
torch_genomics.egg-info/requires.txt
torch_genomics.egg-info/top_level.txt
torchgenomics/__init__.py
torchgenomics/metrics.py
torchgenomics/utils.py
torchgenomics/models/__init__.py
torchgenomics/models/base.py
torchgenomics/models/vae.py
torchgenomics/training/__init__.py
torchgenomics/training/losses.py