Metadata-Version: 2.4
Name: torch-genomics
Version: 2025.12.13
Summary: Deep learning utilities for genomics with PyTorch
Home-page: https://github.com/jolespin/torch-genomics
Author: Josh L. Espinoza
Author-email: jol.espinoz@gmail.com
License: MIT
Keywords: genomics,bioinformatics,deep learning,pytorch,VAE,machine learning
Classifier: Development Status :: 3 - Alpha
Classifier: Intended Audience :: Science/Research
Classifier: Topic :: Scientific/Engineering :: Bio-Informatics
Classifier: Topic :: Scientific/Engineering :: Artificial Intelligence
Classifier: License :: OSI Approved :: MIT License
Classifier: Programming Language :: Python :: 3
Classifier: Programming Language :: Python :: 3.8
Classifier: Programming Language :: Python :: 3.9
Classifier: Programming Language :: Python :: 3.10
Classifier: Programming Language :: Python :: 3.11
Classifier: Programming Language :: Python :: 3.12
Classifier: Programming Language :: Python :: 3.13
Requires-Python: >=3.8
Requires-Dist: pandas
Requires-Dist: pyarrow
Requires-Dist: anndata
Requires-Dist: pyfastx
Requires-Dist: tqdm
Requires-Dist: loguru
Requires-Dist: scikit-learn
Requires-Dist: numpy
Requires-Dist: torch
Requires-Dist: lightning
Requires-Dist: huggingface-hub<1.0,>=0.34.0
Dynamic: author
Dynamic: author-email
Dynamic: classifier
Dynamic: description
Dynamic: description-content-type
Dynamic: home-page
Dynamic: keywords
Dynamic: license
Dynamic: requires-dist
Dynamic: requires-python
Dynamic: summary
